coca_util/__init__.py
coca_util/debug.py
coca_util/line.py
coca_util/ws/Client.py
coca_util/ws/__init__.py
coca_util-0.0.1.dist-info/METADATA
coca_util-0.0.1.dist-info/WHEEL
coca_util-0.0.1.dist-info/RECORD
